pyle.py
pyle_test.py
pyle-0.4.1.data/scripts/pyle
pyle-0.4.1.dist-info/LICENSE
pyle-0.4.1.dist-info/METADATA
pyle-0.4.1.dist-info/WHEEL
pyle-0.4.1.dist-info/top_level.txt
pyle-0.4.1.dist-info/RECORD
